{"nodes": [{"id": "c_users_ppdub_documents_work_weskill_software_fastestcrm_supabase_functions_meta_select_page_index_ts", "label": "index.ts", "file_type": "code", "source_file": "C:\\Users\\ppdub\\Documents\\Work\\Weskill\\Software\\FastestCRM\\supabase\\functions\\meta-select-page\\index.ts", "source_location": "L1"}, {"id": "meta_select_page_index_supabase", "label": "supabase", "file_type": "code", "source_file": "C:\\Users\\ppdub\\Documents\\Work\\Weskill\\Software\\FastestCRM\\supabase\\functions\\meta-select-page\\index.ts", "source_location": "L17"}, {"id": "meta_select_page_index_selectedpage", "label": "selectedPage", "file_type": "code", "source_file": "C:\\Users\\ppdub\\Documents\\Work\\Weskill\\Software\\FastestCRM\\supabase\\functions\\meta-select-page\\index.ts", "source_location": "L93"}, {"id": "meta_select_page_index_tokenexpiresat", "label": "tokenExpiresAt", "file_type": "code", "source_file": "C:\\Users\\ppdub\\Documents\\Work\\Weskill\\Software\\FastestCRM\\supabase\\functions\\meta-select-page\\index.ts", "source_location": "L140"}, {"id": "meta_select_page_index_response", "label": "response", "file_type": "code", "source_file": "C:\\Users\\ppdub\\Documents\\Work\\Weskill\\Software\\FastestCRM\\supabase\\functions\\meta-select-page\\index.ts", "source_location": "L206"}], "edges": [{"source": "c_users_ppdub_documents_work_weskill_software_fastestcrm_supabase_functions_meta_select_page_index_ts", "target": "server_ts", "relation": "imports_from", "context": "import", "confidence": "EXTRACTED", "source_file": "C:\\Users\\ppdub\\Documents\\Work\\Weskill\\Software\\FastestCRM\\supabase\\functions\\meta-select-page\\index.ts", "source_location": "L1", "weight": 1.0}, {"source": "c_users_ppdub_documents_work_weskill_software_fastestcrm_supabase_functions_meta_select_page_index_ts", "target": "supabase_js_2", "relation": "imports_from", "context": "import", "confidence": "EXTRACTED", "source_file": "C:\\Users\\ppdub\\Documents\\Work\\Weskill\\Software\\FastestCRM\\supabase\\functions\\meta-select-page\\index.ts", "source_location": "L2", "weight": 1.0}, {"source": "c_users_ppdub_documents_work_weskill_software_fastestcrm_supabase_functions_meta_select_page_index_ts", "target": "c_users_ppdub_documents_work_weskill_software_fastestcrm_supabase_functions_shared_cors_ts", "relation": "imports_from", "context": "import", "confidence": "EXTRACTED", "source_file": "C:\\Users\\ppdub\\Documents\\Work\\Weskill\\Software\\FastestCRM\\supabase\\functions\\meta-select-page\\index.ts", "source_location": "L3", "weight": 1.0}, {"source": "c_users_ppdub_documents_work_weskill_software_fastestcrm_supabase_functions_meta_select_page_index_ts", "target": "shared_cors_corsheaders", "relation": "imports", "context": "import", "confidence": "EXTRACTED", "source_file": "C:\\Users\\ppdub\\Documents\\Work\\Weskill\\Software\\FastestCRM\\supabase\\functions\\meta-select-page\\index.ts", "source_location": "L3", "weight": 1.0}, {"source": "c_users_ppdub_documents_work_weskill_software_fastestcrm_supabase_functions_meta_select_page_index_ts", "target": "meta_select_page_index_supabase", "relation": "contains", "confidence": "EXTRACTED", "source_file": "C:\\Users\\ppdub\\Documents\\Work\\Weskill\\Software\\FastestCRM\\supabase\\functions\\meta-select-page\\index.ts", "source_location": "L17", "weight": 1.0}, {"source": "c_users_ppdub_documents_work_weskill_software_fastestcrm_supabase_functions_meta_select_page_index_ts", "target": "meta_select_page_index_selectedpage", "relation": "contains", "confidence": "EXTRACTED", "source_file": "C:\\Users\\ppdub\\Documents\\Work\\Weskill\\Software\\FastestCRM\\supabase\\functions\\meta-select-page\\index.ts", "source_location": "L93", "weight": 1.0}, {"source": "c_users_ppdub_documents_work_weskill_software_fastestcrm_supabase_functions_meta_select_page_index_ts", "target": "meta_select_page_index_tokenexpiresat", "relation": "contains", "confidence": "EXTRACTED", "source_file": "C:\\Users\\ppdub\\Documents\\Work\\Weskill\\Software\\FastestCRM\\supabase\\functions\\meta-select-page\\index.ts", "source_location": "L140", "weight": 1.0}, {"source": "c_users_ppdub_documents_work_weskill_software_fastestcrm_supabase_functions_meta_select_page_index_ts", "target": "meta_select_page_index_response", "relation": "contains", "confidence": "EXTRACTED", "source_file": "C:\\Users\\ppdub\\Documents\\Work\\Weskill\\Software\\FastestCRM\\supabase\\functions\\meta-select-page\\index.ts", "source_location": "L206", "weight": 1.0}], "raw_calls": []}