{"nodes": [{"id": "c_users_ppdub_documents_work_weskill_software_fastestcrm_src_hooks_useinvoices_ts", "label": "useInvoices.ts", "file_type": "code", "source_file": "C:\\Users\\ppdub\\Documents\\Work\\Weskill\\Software\\FastestCRM\\src\\hooks\\useInvoices.ts", "source_location": "L1"}, {"id": "hooks_useinvoices_invoiceitem", "label": "InvoiceItem", "file_type": "code", "source_file": "C:\\Users\\ppdub\\Documents\\Work\\Weskill\\Software\\FastestCRM\\src\\hooks\\useInvoices.ts", "source_location": "L8"}, {"id": "hooks_useinvoices_invoice", "label": "Invoice", "file_type": "code", "source_file": "C:\\Users\\ppdub\\Documents\\Work\\Weskill\\Software\\FastestCRM\\src\\hooks\\useInvoices.ts", "source_location": "L23"}, {"id": "hooks_useinvoices_invoicepayment", "label": "InvoicePayment", "file_type": "code", "source_file": "C:\\Users\\ppdub\\Documents\\Work\\Weskill\\Software\\FastestCRM\\src\\hooks\\useInvoices.ts", "source_location": "L60"}, {"id": "hooks_useinvoices_invoiceinput", "label": "InvoiceInput", "file_type": "code", "source_file": "C:\\Users\\ppdub\\Documents\\Work\\Weskill\\Software\\FastestCRM\\src\\hooks\\useInvoices.ts", "source_location": "L73"}, {"id": "hooks_useinvoices_useinvoices", "label": "useInvoices()", "file_type": "code", "source_file": "C:\\Users\\ppdub\\Documents\\Work\\Weskill\\Software\\FastestCRM\\src\\hooks\\useInvoices.ts", "source_location": "L103"}], "edges": [{"source": "c_users_ppdub_documents_work_weskill_software_fastestcrm_src_hooks_useinvoices_ts", "target": "react_query", "relation": "imports_from", "context": "import", "confidence": "EXTRACTED", "source_file": "C:\\Users\\ppdub\\Documents\\Work\\Weskill\\Software\\FastestCRM\\src\\hooks\\useInvoices.ts", "source_location": "L1", "weight": 1.0}, {"source": "c_users_ppdub_documents_work_weskill_software_fastestcrm_src_hooks_useinvoices_ts", "target": "c_users_ppdub_documents_work_weskill_software_fastestcrm_src_integrations_supabase_client_ts", "relation": "imports_from", "context": "import", "confidence": "EXTRACTED", "source_file": "C:\\Users\\ppdub\\Documents\\Work\\Weskill\\Software\\FastestCRM\\src\\hooks\\useInvoices.ts", "source_location": "L2", "weight": 1.0}, {"source": "c_users_ppdub_documents_work_weskill_software_fastestcrm_src_hooks_useinvoices_ts", "target": "supabase_client_supabase", "relation": "imports", "context": "import", "confidence": "EXTRACTED", "source_file": "C:\\Users\\ppdub\\Documents\\Work\\Weskill\\Software\\FastestCRM\\src\\hooks\\useInvoices.ts", "source_location": "L2", "weight": 1.0}, {"source": "c_users_ppdub_documents_work_weskill_software_fastestcrm_src_hooks_useinvoices_ts", "target": "c_users_ppdub_documents_work_weskill_software_fastestcrm_src_hooks_use_toast_ts", "relation": "imports_from", "context": "import", "confidence": "EXTRACTED", "source_file": "C:\\Users\\ppdub\\Documents\\Work\\Weskill\\Software\\FastestCRM\\src\\hooks\\useInvoices.ts", "source_location": "L3", "weight": 1.0}, {"source": "c_users_ppdub_documents_work_weskill_software_fastestcrm_src_hooks_useinvoices_ts", "target": "hooks_use_toast_usetoast", "relation": "imports", "context": "import", "confidence": "EXTRACTED", "source_file": "C:\\Users\\ppdub\\Documents\\Work\\Weskill\\Software\\FastestCRM\\src\\hooks\\useInvoices.ts", "source_location": "L3", "weight": 1.0}, {"source": "c_users_ppdub_documents_work_weskill_software_fastestcrm_src_hooks_useinvoices_ts", "target": "c_users_ppdub_documents_work_weskill_software_fastestcrm_src_hooks_usecompany_ts", "relation": "imports_from", "context": "import", "confidence": "EXTRACTED", "source_file": "C:\\Users\\ppdub\\Documents\\Work\\Weskill\\Software\\FastestCRM\\src\\hooks\\useInvoices.ts", "source_location": "L4", "weight": 1.0}, {"source": "c_users_ppdub_documents_work_weskill_software_fastestcrm_src_hooks_useinvoices_ts", "target": "hooks_usecompany_usecompany", "relation": "imports", "context": "import", "confidence": "EXTRACTED", "source_file": "C:\\Users\\ppdub\\Documents\\Work\\Weskill\\Software\\FastestCRM\\src\\hooks\\useInvoices.ts", "source_location": "L4", "weight": 1.0}, {"source": "c_users_ppdub_documents_work_weskill_software_fastestcrm_src_hooks_useinvoices_ts", "target": "c_users_ppdub_documents_work_weskill_software_fastestcrm_src_hooks_useauth_tsx", "relation": "imports_from", "context": "import", "confidence": "EXTRACTED", "source_file": "C:\\Users\\ppdub\\Documents\\Work\\Weskill\\Software\\FastestCRM\\src\\hooks\\useInvoices.ts", "source_location": "L5", "weight": 1.0}, {"source": "c_users_ppdub_documents_work_weskill_software_fastestcrm_src_hooks_useinvoices_ts", "target": "hooks_useauth_useauth", "relation": "imports", "context": "import", "confidence": "EXTRACTED", "source_file": "C:\\Users\\ppdub\\Documents\\Work\\Weskill\\Software\\FastestCRM\\src\\hooks\\useInvoices.ts", "source_location": "L5", "weight": 1.0}, {"source": "c_users_ppdub_documents_work_weskill_software_fastestcrm_src_hooks_useinvoices_ts", "target": "hooks_useinvoices_invoiceitem", "relation": "contains", "confidence": "EXTRACTED", "source_file": "C:\\Users\\ppdub\\Documents\\Work\\Weskill\\Software\\FastestCRM\\src\\hooks\\useInvoices.ts", "source_location": "L8", "weight": 1.0}, {"source": "c_users_ppdub_documents_work_weskill_software_fastestcrm_src_hooks_useinvoices_ts", "target": "hooks_useinvoices_invoice", "relation": "contains", "confidence": "EXTRACTED", "source_file": "C:\\Users\\ppdub\\Documents\\Work\\Weskill\\Software\\FastestCRM\\src\\hooks\\useInvoices.ts", "source_location": "L23", "weight": 1.0}, {"source": "c_users_ppdub_documents_work_weskill_software_fastestcrm_src_hooks_useinvoices_ts", "target": "hooks_useinvoices_invoicepayment", "relation": "contains", "confidence": "EXTRACTED", "source_file": "C:\\Users\\ppdub\\Documents\\Work\\Weskill\\Software\\FastestCRM\\src\\hooks\\useInvoices.ts", "source_location": "L60", "weight": 1.0}, {"source": "c_users_ppdub_documents_work_weskill_software_fastestcrm_src_hooks_useinvoices_ts", "target": "hooks_useinvoices_invoiceinput", "relation": "contains", "confidence": "EXTRACTED", "source_file": "C:\\Users\\ppdub\\Documents\\Work\\Weskill\\Software\\FastestCRM\\src\\hooks\\useInvoices.ts", "source_location": "L73", "weight": 1.0}, {"source": "c_users_ppdub_documents_work_weskill_software_fastestcrm_src_hooks_useinvoices_ts", "target": "hooks_useinvoices_useinvoices", "relation": "contains", "confidence": "EXTRACTED", "source_file": "C:\\Users\\ppdub\\Documents\\Work\\Weskill\\Software\\FastestCRM\\src\\hooks\\useInvoices.ts", "source_location": "L103", "weight": 1.0}], "raw_calls": [{"caller_nid": "hooks_useinvoices_useinvoices", "callee": "useToast", "is_member_call": false, "source_file": "C:\\Users\\ppdub\\Documents\\Work\\Weskill\\Software\\FastestCRM\\src\\hooks\\useInvoices.ts", "source_location": "L104"}, {"caller_nid": "hooks_useinvoices_useinvoices", "callee": "useQueryClient", "is_member_call": false, "source_file": "C:\\Users\\ppdub\\Documents\\Work\\Weskill\\Software\\FastestCRM\\src\\hooks\\useInvoices.ts", "source_location": "L105"}, {"caller_nid": "hooks_useinvoices_useinvoices", "callee": "useCompany", "is_member_call": false, "source_file": "C:\\Users\\ppdub\\Documents\\Work\\Weskill\\Software\\FastestCRM\\src\\hooks\\useInvoices.ts", "source_location": "L106"}, {"caller_nid": "hooks_useinvoices_useinvoices", "callee": "useAuth", "is_member_call": false, "source_file": "C:\\Users\\ppdub\\Documents\\Work\\Weskill\\Software\\FastestCRM\\src\\hooks\\useInvoices.ts", "source_location": "L107"}, {"caller_nid": "hooks_useinvoices_useinvoices", "callee": "useQuery", "is_member_call": false, "source_file": "C:\\Users\\ppdub\\Documents\\Work\\Weskill\\Software\\FastestCRM\\src\\hooks\\useInvoices.ts", "source_location": "L110"}, {"caller_nid": "hooks_useinvoices_useinvoices", "callee": "useMutation", "is_member_call": false, "source_file": "C:\\Users\\ppdub\\Documents\\Work\\Weskill\\Software\\FastestCRM\\src\\hooks\\useInvoices.ts", "source_location": "L146"}, {"caller_nid": "hooks_useinvoices_useinvoices", "callee": "useMutation", "is_member_call": false, "source_file": "C:\\Users\\ppdub\\Documents\\Work\\Weskill\\Software\\FastestCRM\\src\\hooks\\useInvoices.ts", "source_location": "L200"}, {"caller_nid": "hooks_useinvoices_useinvoices", "callee": "useMutation", "is_member_call": false, "source_file": "C:\\Users\\ppdub\\Documents\\Work\\Weskill\\Software\\FastestCRM\\src\\hooks\\useInvoices.ts", "source_location": "L236"}, {"caller_nid": "hooks_useinvoices_useinvoices", "callee": "useMutation", "is_member_call": false, "source_file": "C:\\Users\\ppdub\\Documents\\Work\\Weskill\\Software\\FastestCRM\\src\\hooks\\useInvoices.ts", "source_location": "L248"}]}